claude_journal/__init__.py
claude_journal/cli.py
claude_journal/git.py
claude_journal/index.py
claude_journal/journal.py
claude_journal/server.py
claude_journal-0.0.4.dist-info/WHEEL
claude_journal-0.0.4.dist-info/entry_points.txt
claude_journal-0.0.4.dist-info/METADATA
claude_journal-0.0.4.dist-info/RECORD
