Metadata-Version: 2.3
Name: claude-journal
Version: 0.0.4
Summary: MCP server that provides journaling capabilities for Claude Code
Author: Andrii Yurchuk
Author-email: Andrii Yurchuk <ay@mntw.re>
License: This is free and unencumbered software released into the public domain.
Requires-Dist: mcp>=1.16.0
Requires-Dist: gitpython>=3.1.45
Requires-Python: >=3.12
